meta_cli/__init__.py
meta_cli/core/__init__.py
meta_cli/core/command_builder.py
meta_cli/core/common_assert.py
meta_cli/tests/__init__.py
meta_cli/tests/base.py
meta_cli/tests/celestia/__init__.py
meta_cli/tests/celestia/fee_allocate.py
meta_cli/tests/celestia/ibc_transfer.py
meta_cli/tests/conftest.py
meta_cli/tests/me_hub/__init__.py
meta_cli/tests/me_hub/gov.py
meta_cli/tests/me_hub/ibc_transfer.py
meta_cli/tests/me_hub/kyc.py
meta_cli/tests/me_hub/staking.py
meta_cli/tests/upgrade/__init__.py
meta_cli/tests/upgrade/conftest.py
meta_cli/tests/upgrade/data_comparison.py
meta_cli/utils/decode_base64.py
meta_cli-0.1.2.dist-info/LICENSE
meta_cli-0.1.2.dist-info/METADATA
meta_cli-0.1.2.dist-info/WHEEL
meta_cli-0.1.2.dist-info/RECORD
