Metadata-Version: 2.3
Name: meta_cli
Version: 0.1.2
Summary: 
Author: will895
Author-email: will8958785@gmail.com
Requires-Python: >=3.10
Classifier: Programming Language :: Python :: 3
Classifier: Programming Language :: Python :: 3.10
Classifier: Programming Language :: Python :: 3.11
Classifier: Programming Language :: Python :: 3.12
Classifier: Programming Language :: Python :: 3.13
Requires-Dist: deepdiff (>=8.4.2,<9.0.0)
Requires-Dist: pytest (>=8.3.5,<9.0.0)
